socaity/__init__.py
socaity/core/socaity_backend_client.py
socaity/core/socaity_service_manager.py
socaity/sdk/__init__.py
socaity/sdk/cache/000e5158-1874-4372-8651-f01943228dc1.json
socaity/sdk/cache/00275b1b-6bea-49ce-9f54-04f25dee29b1.json
socaity/sdk/cache/01265335-2249-43c0-b787-453da9a6fbb0.json
socaity/sdk/cache/0290b9cc-95b5-4a7d-85ac-fecc261777e6.json
socaity/sdk/cache/038ecce9-7616-4853-84c9-1a872f881d0c.json
socaity/sdk/cache/03cfb258-a96d-4104-8661-57b7cb7b034d.json
socaity/sdk/cache/03d99098-c5db-42ad-95ca-693a20555e90.json
socaity/sdk/cache/03d9b9bc-643c-45f1-a286-0e87701b7d1a.json
socaity/sdk/cache/03f4b34b-cd6d-425d-a9b3-6272ae4cb4df.json
socaity/sdk/cache/043a836f-f6d6-4f1a-b0c1-18d68428b666.json
socaity/sdk/cache/04c66564-04a1-43c6-85e1-5ce7a90f4339.json
socaity/sdk/cache/050cedcc-badf-4362-a4c8-8435f9a416b2.json
socaity/sdk/cache/05ee9d66-1243-46d8-92c8-6cd343820df4.json
socaity/sdk/cache/06d2a61c-8197-415c-8cad-f0ee31914e71.json
socaity/sdk/cache/06d50f34-0176-4692-9560-7d20c889e2a7.json
socaity/sdk/cache/06f63a82-ad3f-4325-91f0-a348cd38852e.json
socaity/sdk/cache/07210d2b-cf9b-406b-8daa-4d882008cde1.json
socaity/sdk/cache/08229d1e-901a-45bb-97e5-6291fe34fd3d.json
socaity/sdk/cache/08602100-ad7e-414d-a6e9-7cc24184072a.json
socaity/sdk/cache/08be5d85-7e6f-418c-a99f-e46d51f39428.json
socaity/sdk/cache/09029b7d-3fcc-42b6-b142-6839f9745612.json
socaity/sdk/cache/09115fc3-0100-42e0-b034-3480586c9990.json
socaity/sdk/cache/094dadc4-2eda-47a4-9f6f-8833846a1c70.json
socaity/sdk/cache/09f23f97-71ce-49b0-b6a6-9817472c703f.json
socaity/sdk/cache/0a6c1511-3558-4796-bc3c-94417a13b5a7.json
socaity/sdk/cache/0a8cebfd-16f5-444c-bfbc-f28bc61dd6fd.json
socaity/sdk/cache/0a9bb226-1d9f-4252-bff3-7a5de0c58d55.json
socaity/sdk/cache/0ad6dc5a-4aeb-41e0-ad3b-083361dfe04b.json
socaity/sdk/cache/0b47f390-cedf-429d-9157-dada4f0b747a.json
socaity/sdk/cache/0bbfd0a9-4f09-4f7a-aaa1-faff1b296218.json
socaity/sdk/cache/0c0c9e6c-2cb4-4fa7-87ad-752da9917d37.json
socaity-0.1.6.dist-info/licenses/LICENSE.txt
socaity-0.1.6.dist-info/METADATA
socaity-0.1.6.dist-info/WHEEL
socaity-0.1.6.dist-info/top_level.txt
socaity-0.1.6.dist-info/RECORD
