Metadata-Version: 2.4
Name: socaity
Version: 0.1.6
Summary: Your SDK and model zoo for generative AI. Build AI-powered applications with ease.
Author: SocAIty
Project-URL: Repository, https://github.com/SocAIty/socaity
Project-URL: Homepage, https://www.socaity.ai
Requires-Python: >=3.8
License-File: LICENSE.txt
Requires-Dist: tqdm
Requires-Dist: httpx
Requires-Dist: fastsdk>=0.2.6
Requires-Dist: media-toolkit[VideoFile]>=00.02.08
Requires-Dist: singleton_decorator==1.0.0
Provides-Extra: dev
Requires-Dist: pytest; extra == "dev"
Dynamic: license-file
